README.md
setup.py
AutoBUlidVocabulary/__init__.py
AutoBUlidVocabulary/vocab.py
AutoBUlidVocabulary.egg-info/PKG-INFO
AutoBUlidVocabulary.egg-info/SOURCES.txt
AutoBUlidVocabulary.egg-info/dependency_links.txt
AutoBUlidVocabulary.egg-info/top_level.txt
test/test.py