Metadata-Version: 1.0
Name: AutoBUlidVocabulary
Version: 0.1.0.11572550988.7617092
Summary: Auto BUlid Vocabulary
Home-page: https://github.com/napoler/AutoBUlidVocabulary
Author: Terry Chan
Author-email: napoler2008@gmail.com
License: UNKNOWN
Platform: UNKNOWN
